{
  "patients": [
    {
      "id": "550e8400-e29b-41d4-a716-446655440001",
      "firstName": "John",
      "lastName": "Doe",
      "dateOfBirth": "1985-06-15T00:00:00Z",
      "email": "john.doe@email.com",
      "phone": "\u002B1-555-0100",
      "address": {
        "street": "123 Main St",
        "city": "Springfield",
        "state": "IL",
        "zipCode": "62701"
      },
      "createdAt": "2025-01-15T10:30:00Z",
      "updatedAt": "2025-01-15T10:30:00Z"
    },
    {
      "id": "550e8400-e29b-41d4-a716-446655440002",
      "firstName": "Jane",
      "lastName": "Smith",
      "dateOfBirth": "1990-03-22T00:00:00Z",
      "email": "jane.smith@email.com",
      "phone": "\u002B1-555-0101",
      "address": {
        "street": "456 Oak Ave",
        "city": "Springfield",
        "state": "IL",
        "zipCode": "62702"
      },
      "createdAt": "2025-02-10T14:20:00Z",
      "updatedAt": "2025-02-10T14:20:00Z"
    },
    {
      "id": "89dda93b-1fb3-4fa6-a736-83305af57447",
      "firstName": "John",
      "lastName": "Doe",
      "dateOfBirth": "2025-09-10T00:00:00",
      "email": "john.doe@gmail.com",
      "phone": "123-456-789",
      "address": {
        "street": "42 Wallaby Street",
        "city": "Melbourne",
        "state": "Austrailia",
        "zipCode": "123456"
      },
      "createdAt": "2025-09-30T01:12:48.684941Z",
      "updatedAt": "2025-09-30T01:12:48.684948Z"
    }
  ],
  "doctors": [
    {
      "id": "660e8400-e29b-41d4-a716-446655440001",
      "firstName": "Sarah",
      "lastName": "Johnson",
      "specialization": "General Practice",
      "email": "dr.johnson@clinic.com",
      "phone": "\u002B1-555-0200",
      "consultationFee": 150.00,
      "availability": [
        {
          "dayOfWeek": 1,
          "startTime": "09:00",
          "endTime": "17:00"
        },
        {
          "dayOfWeek": 2,
          "startTime": "09:00",
          "endTime": "17:00"
        },
        {
          "dayOfWeek": 3,
          "startTime": "09:00",
          "endTime": "17:00"
        }
      ],
      "createdAt": "2025-01-01T08:00:00Z"
    },
    {
      "id": "660e8400-e29b-41d4-a716-446655440002",
      "firstName": "Michael",
      "lastName": "Chen",
      "specialization": "Cardiology",
      "email": "dr.chen@clinic.com",
      "phone": "\u002B1-555-0201",
      "consultationFee": 250.00,
      "availability": [
        {
          "dayOfWeek": 2,
          "startTime": "10:00",
          "endTime": "16:00"
        },
        {
          "dayOfWeek": 4,
          "startTime": "10:00",
          "endTime": "16:00"
        }
      ],
      "createdAt": "2025-01-01T08:00:00Z"
    }
  ],
  "appointments": [
    {
      "id": "4a45836d-a6e3-4c2b-8b00-9a199c044c7b",
      "patientId": "89dda93b-1fb3-4fa6-a736-83305af57447",
      "doctorId": "660e8400-e29b-41d4-a716-446655440002",
      "appointmentDateTime": "2025-09-04T01:13:00Z",
      "duration": 30,
      "status": 0,
      "reason": "Checkup123",
      "notes": "",
      "createdAt": "2025-09-30T01:13:46.133167Z",
      "updatedAt": "2025-09-30T01:13:46.133216Z"
    },
    {
      "id": "c30bae2f-b111-4f9f-a321-3913c363167c",
      "patientId": "89dda93b-1fb3-4fa6-a736-83305af57447",
      "doctorId": "660e8400-e29b-41d4-a716-446655440002",
      "appointmentDateTime": "2025-09-12T01:15:00Z",
      "duration": 30,
      "status": 0,
      "reason": "Checkup Again",
      "notes": "",
      "createdAt": "2025-09-30T01:16:01.726072Z",
      "updatedAt": "2025-09-30T01:16:01.726172Z"
    },
    {
      "id": "10ef4af5-e7c0-4678-8abd-584472eff7df",
      "patientId": "550e8400-e29b-41d4-a716-446655440002",
      "doctorId": "660e8400-e29b-41d4-a716-446655440001",
      "appointmentDateTime": "2025-09-12T01:25:00Z",
      "duration": 30,
      "status": 0,
      "reason": "Check up",
      "notes": "",
      "createdAt": "2025-09-30T01:24:58.172152Z",
      "updatedAt": "2025-09-30T01:24:58.172199Z"
    },
    {
      "id": "01a2cc89-03f9-453e-b977-1e9c24f77ee2",
      "patientId": "89dda93b-1fb3-4fa6-a736-83305af57447",
      "doctorId": "660e8400-e29b-41d4-a716-446655440001",
      "appointmentDateTime": "2025-09-26T01:25:00Z",
      "duration": 30,
      "status": 0,
      "reason": "checkup again",
      "notes": "",
      "createdAt": "2025-09-30T01:25:35.097084Z",
      "updatedAt": "2025-09-30T01:25:35.097084Z"
    },
    {
      "id": "f35b07e8-47b9-4632-a0a6-3af6309b830a",
      "patientId": "550e8400-e29b-41d4-a716-446655440002",
      "doctorId": "660e8400-e29b-41d4-a716-446655440002",
      "appointmentDateTime": "2025-09-12T01:32:00Z",
      "duration": 30,
      "status": 0,
      "reason": "Check up",
      "notes": "",
      "createdAt": "2025-09-30T01:32:26.553037Z",
      "updatedAt": "2025-09-30T01:32:26.553043Z"
    }
  ],
  "invoices": [
    {
      "id": "b8ec2ac2-e78a-4eaf-a7f6-fbe418bf7ace",
      "appointmentId": "4a45836d-a6e3-4c2b-8b00-9a199c044c7b",
      "patientId": "89dda93b-1fb3-4fa6-a736-83305af57447",
      "amount": 250.00,
      "tax": 20.0000,
      "totalAmount": 270.0000,
      "status": 0,
      "items": [
        {
          "description": "Consultation Fee - Dr. Michael Chen",
          "amount": 250.00
        }
      ],
      "generatedAt": "2025-09-30T01:13:46.141371Z",
      "dueDate": "2025-10-30T01:13:46.141394Z"
    },
    {
      "id": "7b501487-154d-4947-9e1d-69ff2818b8f0",
      "appointmentId": "c30bae2f-b111-4f9f-a321-3913c363167c",
      "patientId": "89dda93b-1fb3-4fa6-a736-83305af57447",
      "amount": 250.00,
      "tax": 20.0000,
      "totalAmount": 270.0000,
      "status": 0,
      "items": [
        {
          "description": "Consultation Fee - Dr. Michael Chen",
          "amount": 250.00
        }
      ],
      "generatedAt": "2025-09-30T01:16:01.729213Z",
      "dueDate": "2025-10-30T01:16:01.729213Z"
    },
    {
      "id": "8e2f5fbc-e057-4c7d-ba8d-7dab0dee8d52",
      "appointmentId": "10ef4af5-e7c0-4678-8abd-584472eff7df",
      "patientId": "550e8400-e29b-41d4-a716-446655440002",
      "amount": 150.00,
      "tax": 12.0000,
      "totalAmount": 162.0000,
      "status": 1,
      "items": [
        {
          "description": "Consultation Fee - Dr. Sarah Johnson",
          "amount": 150.00
        }
      ],
      "generatedAt": "2025-09-30T01:24:58.173105Z",
      "dueDate": "2025-10-30T01:24:58.173105Z"
    },
    {
      "id": "8c8c1dce-45db-4ea1-8147-605392186439",
      "appointmentId": "01a2cc89-03f9-453e-b977-1e9c24f77ee2",
      "patientId": "89dda93b-1fb3-4fa6-a736-83305af57447",
      "amount": 150.00,
      "tax": 12.0000,
      "totalAmount": 162.0000,
      "status": 1,
      "items": [
        {
          "description": "Consultation Fee - Dr. Sarah Johnson",
          "amount": 150.00
        }
      ],
      "generatedAt": "2025-09-30T01:25:35.098892Z",
      "dueDate": "2025-10-30T01:25:35.098892Z"
    },
    {
      "id": "9f858ecd-31c8-4bc0-bc95-abeb63a1494f",
      "appointmentId": "f35b07e8-47b9-4632-a0a6-3af6309b830a",
      "patientId": "550e8400-e29b-41d4-a716-446655440002",
      "amount": 250.00,
      "tax": 20.0000,
      "totalAmount": 270.0000,
      "status": 1,
      "items": [
        {
          "description": "Consultation Fee - Dr. Michael Chen",
          "amount": 250.00
        }
      ],
      "generatedAt": "2025-09-30T01:32:26.560098Z",
      "dueDate": "2025-10-30T01:32:26.560098Z"
    }
  ],
  "payments": [
    {
      "id": "48608231-ff12-4980-a7f6-6aaca5dda7d6",
      "invoiceId": "8e2f5fbc-e057-4c7d-ba8d-7dab0dee8d52",
      "amount": 162,
      "paymentMethod": 2,
      "transactionId": "txn_c9dfc285440b",
      "status": 1,
      "processedAt": "2025-09-30T01:25:17.214576Z"
    },
    {
      "id": "8cd98e9b-7875-4bb2-8744-22ce03b4de56",
      "invoiceId": "8c8c1dce-45db-4ea1-8147-605392186439",
      "amount": 162,
      "paymentMethod": 3,
      "transactionId": "txn_1a03718757ea",
      "status": 1,
      "processedAt": "2025-09-30T01:25:41.873676Z"
    },
    {
      "id": "e13baefd-7b02-4a72-88e7-a3f4198bac7c",
      "invoiceId": "9f858ecd-31c8-4bc0-bc95-abeb63a1494f",
      "amount": 270,
      "paymentMethod": 0,
      "transactionId": "txn_e32f8882fdb2",
      "status": 1,
      "processedAt": "2025-09-30T01:32:30.428966Z"
    }
  ]
}